{
    "name": "Global Information",
    "numberOfRequests": {
        "total": 3,
        "ok": 3,
        "ko": 0
    },
    "minResponseTime": {
        "total": 109,
        "ok": 109,
        "ko": 0
    },
    "maxResponseTime": {
        "total": 222,
        "ok": 222,
        "ko": 0
    },
    "meanResponseTime": {
        "total": 149,
        "ok": 149,
        "ko": 0
    },
    "standardDeviation": {
        "total": 52,
        "ok": 52,
        "ko": 0
    },
    "percentiles1": {
        "total": 116,
        "ok": 116,
        "ko": 0
    },
    "percentiles2": {
        "total": 169,
        "ok": 169,
        "ko": 0
    },
    "percentiles3": {
        "total": 211,
        "ok": 211,
        "ko": 0
    },
    "percentiles4": {
        "total": 220,
        "ok": 220,
        "ko": 0
    },
    "group1": {
    "name": "t < 800 ms",
    "count": 3,
    "percentage": 100
},
    "group2": {
    "name": "800 ms < t < 1200 ms",
    "count": 0,
    "percentage": 0
},
    "group3": {
    "name": "t > 1200 ms",
    "count": 0,
    "percentage": 0
},
    "group4": {
    "name": "failed",
    "count": 0,
    "percentage": 0
},
    "meanNumberOfRequestsPerSecond": {
        "total": 1.5,
        "ok": 1.5,
        "ko": 0
    }
}